{"version": 0.6, "generator": "Overpass API 0.7.62.11 87bfad18", "osm3s": {"timestamp_osm_base": "2026-03-30T17:40:59Z", "copyright": "The data included in this document is from www.openstreetmap.org. The data is made available under ODbL."}, "elements": [{"type": "node", "id": 6789350485, "lat": 35.463335, "lon": -94.7075799, "tags": {"amenity": "fire_station", "name": "Central Fire Department"}}, {"type": "node", "id": 7262208486, "lat": 35.3657833, "lon": -94.7856991, "tags": {"amenity": "fire_station", "check_date": "2024-03-23", "name": "Brent"}}, {"type": "node", "id": 7264079686, "lat": 35.259549, "lon": -94.4786208, "tags": {"amenity": "fire_station", "name": "Pocola Fire-Rescue Station1"}}, {"type": "node", "id": 10929746045, "lat": 35.4152479, "lon": -94.5147897}, {"type": "node", "id": 10929746046, "lat": 35.4151978, "lon": -94.5147896}, {"type": "node", "id": 10929746047, "lat": 35.4151977, "lon": -94.514922}, {"type": "node", "id": 10929746048, "lat": 35.4153645, "lon": -94.5149331}, {"type": "node", "id": 10929746049, "lat": 35.4153664, "lon": -94.514404}, {"type": "node", "id": 10929746050, "lat": 35.415275, "lon": -94.5144039}, {"type": "node", "id": 10929746051, "lat": 35.4152732, "lon": -94.5145645}, {"type": "node", "id": 10929746052, "lat": 35.4152481, "lon": -94.5145645}, {"type": "node", "id": 11495725899, "lat": 35.3894236, "lon": -94.6922181}, {"type": "node", "id": 11495725900, "lat": 35.3893496, "lon": -94.6921588}, {"type": "node", "id": 11495725901, "lat": 35.3894282, "lon": -94.692011}, {"type": "node", "id": 11495725902, "lat": 35.3893924, "lon": -94.6919824}, {"type": "node", "id": 11495725903, "lat": 35.3894631, "lon": -94.6918495}, {"type": "node", "id": 11495725904, "lat": 35.3896071, "lon": -94.6919647}, {"type": "node", "id": 11495725905, "lat": 35.3895367, "lon": -94.6920971}, {"type": "node", "id": 11495725906, "lat": 35.3895025, "lon": -94.6920698}, {"type": "way", "id": 1176351579, "nodes": [10929746045, 10929746046, 10929746047, 10929746048, 10929746049, 10929746050, 10929746051, 10929746052, 10929746045], "tags": {"amenity": "fire_station", "building": "fire_station", "name": "Roland Fire Department", "phone": "+1-918-427-3253"}}, {"type": "way", "id": 1237648431, "nodes": [11495725899, 11495725900, 11495725901, 11495725902, 11495725903, 11495725904, 11495725905, 11495725906, 11495725899], "tags": {"amenity": "fire_station", "name": "Gans Fire Department", "website": "https://m.facebook.com/people/Gans-Volunteer-Fire-Department/100064447013971/"}}]}